treetop_client/client.py
treetop_client/models.py
treetop_client-0.0.6.dist-info/METADATA
treetop_client-0.0.6.dist-info/WHEEL
treetop_client-0.0.6.dist-info/licenses/LICENSE
treetop_client-0.0.6.dist-info/RECORD
