Metadata-Version: 2.4
Name: treetop-client
Version: 0.0.6
Summary: Python client library for the Treetop policy server
Project-URL: Homepage, https://github.com/terjekv/treetop-client-python
Project-URL: Issues, https://github.com/terjekv/treetop-client-python/issues
Author-email: Terje Kvernes <terje@kvernes.no>
License: MIT
License-File: LICENSE
Requires-Python: >=3.12
Requires-Dist: httpx<0.29.0,>=0.28.1
Provides-Extra: dev
Requires-Dist: pyright>=1.0.0; extra == 'dev'
Requires-Dist: pytest-httpx>=0.36.0; extra == 'dev'
Requires-Dist: pytest>=9.0.0; extra == 'dev'
